tiktok_simple_scraper/__init__.py
tiktok_simple_scraper/account.py
tiktok_simple_scraper/entities.py
tiktok_simple_scraper/mstoken.py
tiktok_simple_scraper/opts.py
tiktok_simple_scraper/tiktok.py
tiktok_simple_scraper/verify_fp.py
tiktok_simple_scraper/x_bogus.py
tiktok_simple_scraper-0.0.9.dist-info/LICENCE
tiktok_simple_scraper-0.0.9.dist-info/METADATA
tiktok_simple_scraper-0.0.9.dist-info/WHEEL
tiktok_simple_scraper-0.0.9.dist-info/top_level.txt
tiktok_simple_scraper-0.0.9.dist-info/RECORD
