Metadata-Version: 2.1
Name: tiktok_simple_scraper
Version: 0.0.9
Summary: A simple scraper for Tiktok
Home-page: https://github.com/Eitol/tiktok_simple_scraper
Author: Hector Oliveros
Author-email: hector.oliveros.leon@gmail.com
License: MIT
Classifier: Programming Language :: Python :: 3
Classifier: License :: OSI Approved :: MIT License
Classifier: Operating System :: OS Independent
Requires-Python: >=3.10
License-File: LICENCE
Requires-Dist: pydantic ~=2.7.1
Requires-Dist: requests ~=2.31.0
Requires-Dist: beautifulsoup4 ~=4.12.3
Requires-Dist: python-dateutil ~=2.9.0.post0
Requires-Dist: dateparser ~=1.2.0
Requires-Dist: urllib3 ~=2.2.1
